{
  "customUrlSource" : "/custom/artifactList",
  "basisTable" : "__MOCK_TABLE__",
  "children" : [ {
    "name" : "ArtifactTypes",
    "basisTable" : "__MOCK_TABLE__",
    "children" : [ {
      "name" : "ModuleArtifacts",
      "basisTable" : "__MOCK_TABLE__",
      "fields" : [ {
        "name" : "ArtifactName",
        "basisColumn" : "__MOCK_STRING__"
      }, {
        "name" : "ArtifactOutput",
        "basisColumn" : "__MOCK_STRING__"
      } ]
    } ],
    "fields" : [ {
      "name" : "ArtifactType",
      "basisColumn" : "__MOCK_STRING__"
    } ]
  } ],
  "fields" : [ {
    "name" : "ModuleName",
    "basisColumn" : "__MOCK_STRING__"
  } ]
}